{
  "team_id": 17,
  "team_name": "Dallas Cowboys",
  "total_players": 55,
  "players": {
    "1700": {
      "player_id": 1700,
      "first_name": "Dak",
      "last_name": "Prescott",
      "number": 4,
      "positions": [
        "quarterback"
      ],
      "team_id": 17,
      "attributes": {
        "overall": 87,
        "speed": 76,
        "accuracy": 86,
        "arm_strength": 84,
        "awareness": 85,
        "discipline": 84,
        "composure": 86,
        "experience": 86,
        "penalty_technique": 85,
        "leadership": 85
      }
    },
    "1701": {
      "player_id": 1701,
      "first_name": "Javonte",
      "last_name": "Williams",
      "number": 33,
      "positions": [
        "running_back"
      ],
      "team_id": 17,
      "attributes": {
        "overall": 82,
        "speed": 84,
        "acceleration": 85,
        "elusiveness": 81,
        "power": 84,
        "discipline": 83,
        "composure": 82,
        "experience": 78,
        "penalty_technique": 84,
        "endurance": 84
      }
    },
    "1702": {
      "player_id": 1702,
      "first_name": "CeeDee",
      "last_name": "Lamb",
      "number": 88,
      "positions": [
        "wide_receiver"
      ],
      "team_id": 17,
      "attributes": {
        "overall": 91,
        "speed": 88,
        "acceleration": 89,
        "hands": 92,
        "route_running": 91,
        "discipline": 87,
        "composure": 86,
        "experience": 81,
        "penalty_technique": 88,
        "awareness": 89
      }
    },
    "1703": {
      "player_id": 1703,
      "first_name": "George",
      "last_name": "Pickens",
      "number": 3,
      "positions": [
        "wide_receiver"
      ],
      "team_id": 17,
      "attributes": {
        "overall": 84,
        "speed": 87,
        "acceleration": 88,
        "hands": 85,
        "route_running": 83,
        "discipline": 78,
        "composure": 79,
        "experience": 77,
        "penalty_technique": 80,
        "awareness": 82
      }
    },
    "1704": {
      "player_id": 1704,
      "first_name": "Jake",
      "last_name": "Ferguson",
      "number": 87,
      "positions": [
        "tight_end"
      ],
      "team_id": 17,
      "attributes": {
        "overall": 82,
        "speed": 78,
        "acceleration": 77,
        "hands": 83,
        "route_running": 80,
        "blocking": 83,
        "discipline": 84,
        "composure": 82,
        "experience": 77,
        "penalty_technique": 84,
        "awareness": 82
      }
    },
    "1705": {
      "player_id": 1705,
      "first_name": "Tyler",
      "last_name": "Smith",
      "number": 73,
      "positions": [
        "offensive_tackle"
      ],
      "team_id": 17,
      "attributes": {
        "overall": 80,
        "speed": 71,
        "acceleration": 73,
        "pass_blocking": 81,
        "run_blocking": 80,
        "discipline": 81,
        "composure": 80,
        "experience": 77,
        "penalty_technique": 82,
        "awareness": 79
      }
    },
    "1706": {
      "player_id": 1706,
      "first_name": "Cooper",
      "last_name": "Beebe",
      "number": 52,
      "positions": [
        "center"
      ],
      "team_id": 17,
      "attributes": {
        "overall": 78,
        "speed": 67,
        "acceleration": 69,
        "pass_blocking": 79,
        "run_blocking": 78,
        "discipline": 82,
        "composure": 80,
        "experience": 74,
        "penalty_technique": 82,
        "awareness": 78
      }
    },
    "1707": {
      "player_id": 1707,
      "first_name": "Trevon",
      "last_name": "Diggs",
      "number": 7,
      "positions": [
        "cornerback"
      ],
      "team_id": 17,
      "attributes": {
        "overall": 86,
        "speed": 88,
        "acceleration": 89,
        "coverage": 87,
        "press": 85,
        "discipline": 82,
        "composure": 81,
        "experience": 80,
        "penalty_technique": 83,
        "awareness": 86
      }
    },
    "1708": {
      "player_id": 1708,
      "first_name": "Micah",
      "last_name": "Parsons",
      "number": 11,
      "positions": [
        "linebacker",
        "defensive_end"
      ],
      "team_id": 17,
      "attributes": {
        "overall": 94,
        "speed": 90,
        "acceleration": 91,
        "pass_rush": 93,
        "tackle": 91,
        "coverage": 85,
        "discipline": 86,
        "composure": 84,
        "experience": 79,
        "penalty_technique": 87,
        "awareness": 89
      }
    },
    "1709": {
      "player_id": 1709,
      "first_name": "DaRon",
      "last_name": "Payne",
      "number": 94,
      "positions": [
        "defensive_tackle"
      ],
      "team_id": 17,
      "attributes": {
        "overall": 87,
        "speed": 78,
        "acceleration": 79,
        "pass_rush": 84,
        "run_defense": 89,
        "discipline": 85,
        "composure": 83,
        "experience": 82,
        "penalty_technique": 86,
        "awareness": 84
      }
    },
    "1710": {
      "player_id": 1710,
      "first_name": "Donovan",
      "last_name": "Wilson",
      "number": 37,
      "positions": [
        "safety"
      ],
      "team_id": 17,
      "attributes": {
        "overall": 84,
        "speed": 83,
        "acceleration": 84,
        "coverage": 83,
        "tackle": 85,
        "discipline": 84,
        "composure": 83,
        "experience": 81,
        "penalty_technique": 85,
        "awareness": 84
      }
    },
    "1711": {
      "player_id": 1711,
      "first_name": "Brandon",
      "last_name": "Aubrey",
      "number": 17,
      "positions": [
        "kicker"
      ],
      "team_id": 17,
      "attributes": {
        "overall": 86,
        "speed": 62,
        "acceleration": 64,
        "kick_power": 90,
        "kick_accuracy": 88,
        "discipline": 88,
        "composure": 85,
        "experience": 76,
        "penalty_technique": 90,
        "clutch": 87
      }
    },
    "1712": {
      "player_id": 1712,
      "first_name": "Joe",
      "last_name": "Milton III",
      "number": 10,
      "positions": ["quarterback"],
      "team_id": 17,
      "attributes": {
        "overall": 72,
        "speed": 82,
        "accuracy": 70,
        "arm_strength": 88,
        "awareness": 68,
        "discipline": 75,
        "composure": 70,
        "experience": 68,
        "penalty_technique": 75,
        "leadership": 70,
        "mobility": 85,
        "potential": 78
      }
    },
    "1713": {
      "player_id": 1713,
      "first_name": "Miles",
      "last_name": "Sanders",
      "number": 24,
      "positions": ["running_back"],
      "team_id": 17,
      "attributes": {
        "overall": 81,
        "speed": 88,
        "strength": 78,
        "agility": 85,
        "hands": 80,
        "awareness": 82,
        "discipline": 82,
        "composure": 82,
        "experience": 82,
        "penalty_technique": 82,
        "elusiveness": 85,
        "vision": 82,
        "receiving": 80
      }
    },
    "1714": {
      "player_id": 1714,
      "first_name": "Jaydon",
      "last_name": "Blue",
      "number": 23,
      "positions": ["running_back"],
      "team_id": 17,
      "attributes": {
        "overall": 74,
        "speed": 88,
        "strength": 75,
        "agility": 85,
        "hands": 75,
        "awareness": 68,
        "discipline": 72,
        "composure": 68,
        "experience": 62,
        "penalty_technique": 72,
        "elusiveness": 88,
        "vision": 75,
        "potential": 82
      }
    },
    "1715": {
      "player_id": 1715,
      "first_name": "Hunter",
      "last_name": "Luepke",
      "number": 40,
      "positions": ["fullback"],
      "team_id": 17,
      "attributes": {
        "overall": 76,
        "speed": 75,
        "strength": 85,
        "agility": 72,
        "hands": 78,
        "awareness": 78,
        "discipline": 82,
        "composure": 78,
        "experience": 70,
        "penalty_technique": 82,
        "blocking": 85,
        "power": 85,
        "receiving": 75
      }
    },
    "1716": {
      "player_id": 1716,
      "first_name": "Jalen",
      "last_name": "Tolbert",
      "number": 1,
      "positions": ["wide_receiver"],
      "team_id": 17,
      "attributes": {
        "overall": 78,
        "speed": 82,
        "strength": 78,
        "agility": 80,
        "hands": 82,
        "awareness": 78,
        "discipline": 80,
        "composure": 78,
        "experience": 75,
        "penalty_technique": 80,
        "route_running": 80,
        "release": 82,
        "catching": 82
      }
    },
    "1717": {
      "player_id": 1717,
      "first_name": "KaVontae",
      "last_name": "Turpin",
      "number": 9,
      "positions": ["wide_receiver"],
      "team_id": 17,
      "attributes": {
        "overall": 79,
        "speed": 95,
        "strength": 68,
        "agility": 92,
        "hands": 75,
        "awareness": 78,
        "discipline": 78,
        "composure": 78,
        "experience": 75,
        "penalty_technique": 78,
        "route_running": 75,
        "return_skills": 95,
        "elusiveness": 92
      }
    },
    "1718": {
      "player_id": 1718,
      "first_name": "Ryan",
      "last_name": "Flournoy",
      "number": 19,
      "positions": ["wide_receiver"],
      "team_id": 17,
      "attributes": {
        "overall": 71,
        "speed": 80,
        "strength": 72,
        "agility": 78,
        "hands": 78,
        "awareness": 68,
        "discipline": 72,
        "composure": 68,
        "experience": 68,
        "penalty_technique": 72,
        "route_running": 75,
        "release": 78,
        "catching": 78,
        "development": 75
      }
    },
    "1719": {
      "player_id": 1719,
      "first_name": "Luke",
      "last_name": "Schoonmaker",
      "number": 86,
      "positions": ["tight_end"],
      "team_id": 17,
      "attributes": {
        "overall": 75,
        "speed": 75,
        "strength": 82,
        "agility": 72,
        "hands": 78,
        "awareness": 75,
        "discipline": 80,
        "composure": 75,
        "experience": 70,
        "penalty_technique": 80,
        "route_running": 75,
        "blocking": 80,
        "catching": 78
      }
    },
    "1720": {
      "player_id": 1720,
      "first_name": "Brevyn",
      "last_name": "Spann-Ford",
      "number": 89,
      "positions": ["tight_end"],
      "team_id": 17,
      "attributes": {
        "overall": 72,
        "speed": 72,
        "strength": 78,
        "agility": 68,
        "hands": 75,
        "awareness": 68,
        "discipline": 75,
        "composure": 68,
        "experience": 68,
        "penalty_technique": 75,
        "route_running": 68,
        "blocking": 78,
        "catching": 75,
        "development": 75
      }
    },
    "1721": {
      "player_id": 1721,
      "first_name": "Tyler",
      "last_name": "Guyton",
      "number": 79,
      "positions": ["left_tackle"],
      "team_id": 17,
      "attributes": {
        "overall": 78,
        "speed": 75,
        "strength": 82,
        "agility": 75,
        "awareness": 72,
        "discipline": 75,
        "composure": 72,
        "experience": 62,
        "penalty_technique": 75,
        "pass_blocking": 78,
        "run_blocking": 78,
        "athleticism": 82,
        "potential": 85
      }
    },
    "1722": {
      "player_id": 1722,
      "first_name": "Terence",
      "last_name": "Steele",
      "number": 78,
      "positions": ["right_tackle"],
      "team_id": 17,
      "attributes": {
        "overall": 79,
        "speed": 72,
        "strength": 85,
        "agility": 70,
        "awareness": 78,
        "discipline": 80,
        "composure": 78,
        "experience": 78,
        "penalty_technique": 80,
        "pass_blocking": 80,
        "run_blocking": 82,
        "anchor": 85,
        "consistency": 78
      }
    },
    "1723": {
      "player_id": 1723,
      "first_name": "Tyler",
      "last_name": "Smith",
      "number": 70,
      "positions": ["left_guard"],
      "team_id": 17,
      "attributes": {
        "overall": 82,
        "speed": 72,
        "strength": 85,
        "agility": 75,
        "awareness": 82,
        "discipline": 85,
        "composure": 82,
        "experience": 78,
        "penalty_technique": 85,
        "pass_blocking": 82,
        "run_blocking": 85,
        "athleticism": 80,
        "technique": 82
      }
    },
    "1724": {
      "player_id": 1724,
      "first_name": "Tyler",
      "last_name": "Booker",
      "number": 75,
      "positions": ["right_guard"],
      "team_id": 17,
      "attributes": {
        "overall": 76,
        "speed": 68,
        "strength": 82,
        "agility": 70,
        "awareness": 75,
        "discipline": 78,
        "composure": 75,
        "experience": 62,
        "penalty_technique": 78,
        "pass_blocking": 75,
        "run_blocking": 80,
        "power": 82,
        "potential": 82
      }
    },
    "1725": {
      "player_id": 1725,
      "first_name": "T.J.",
      "last_name": "Bass",
      "number": 64,
      "positions": ["guard"],
      "team_id": 17,
      "attributes": {
        "overall": 73,
        "speed": 68,
        "strength": 78,
        "agility": 68,
        "awareness": 72,
        "discipline": 78,
        "composure": 72,
        "experience": 70,
        "penalty_technique": 78,
        "pass_blocking": 72,
        "run_blocking": 75,
        "versatility": 80,
        "backup_value": 75
      }
    },
    "1726": {
      "player_id": 1726,
      "first_name": "Brock",
      "last_name": "Hoffman",
      "number": 65,
      "positions": ["center"],
      "team_id": 17,
      "attributes": {
        "overall": 71,
        "speed": 68,
        "strength": 75,
        "agility": 68,
        "awareness": 75,
        "discipline": 78,
        "composure": 72,
        "experience": 68,
        "penalty_technique": 78,
        "pass_blocking": 70,
        "run_blocking": 72,
        "snap_accuracy": 80,
        "backup_center": 75
      }
    },
    "1727": {
      "player_id": 1727,
      "first_name": "Nate",
      "last_name": "Thomas",
      "number": 77,
      "positions": ["tackle"],
      "team_id": 17,
      "attributes": {
        "overall": 70,
        "speed": 70,
        "strength": 78,
        "agility": 68,
        "awareness": 68,
        "discipline": 72,
        "composure": 68,
        "experience": 68,
        "penalty_technique": 72,
        "pass_blocking": 68,
        "run_blocking": 72,
        "development": 72,
        "depth": 75
      }
    },
    "1728": {
      "player_id": 1728,
      "first_name": "Ajani",
      "last_name": "Cornelius",
      "number": 76,
      "positions": ["tackle"],
      "team_id": 17,
      "attributes": {
        "overall": 69,
        "speed": 70,
        "strength": 75,
        "agility": 68,
        "awareness": 65,
        "discipline": 70,
        "composure": 65,
        "experience": 62,
        "penalty_technique": 70,
        "pass_blocking": 68,
        "run_blocking": 70,
        "potential": 75,
        "development": 72
      }
    },
    "1729": {
      "player_id": 1729,
      "first_name": "Hakeem",
      "last_name": "Adeniji",
      "number": 74,
      "positions": ["tackle"],
      "team_id": 17,
      "attributes": {
        "overall": 71,
        "speed": 70,
        "strength": 78,
        "agility": 68,
        "awareness": 72,
        "discipline": 75,
        "composure": 72,
        "experience": 75,
        "penalty_technique": 75,
        "pass_blocking": 70,
        "run_blocking": 72,
        "versatility": 78,
        "experience_value": 78
      }
    },
    "1730": {
      "player_id": 1730,
      "first_name": "Dante",
      "last_name": "Fowler",
      "number": 55,
      "positions": ["defensive_end"],
      "team_id": 17,
      "attributes": {
        "overall": 82,
        "speed": 85,
        "strength": 82,
        "agility": 82,
        "awareness": 85,
        "discipline": 82,
        "composure": 82,
        "experience": 88,
        "penalty_technique": 82,
        "pass_rush": 85,
        "run_defense": 78,
        "power_moves": 80,
        "finesse_moves": 85,
        "veteran_presence": 88
      }
    },
    "1731": {
      "player_id": 1731,
      "first_name": "Marshawn",
      "last_name": "Kneeland",
      "number": 92,
      "positions": ["defensive_end"],
      "team_id": 17,
      "attributes": {
        "overall": 76,
        "speed": 80,
        "strength": 82,
        "agility": 78,
        "awareness": 72,
        "discipline": 75,
        "composure": 72,
        "experience": 68,
        "penalty_technique": 75,
        "pass_rush": 78,
        "run_defense": 78,
        "power_moves": 80,
        "motor": 82,
        "potential": 82
      }
    },
    "1732": {
      "player_id": 1732,
      "first_name": "Donovan",
      "last_name": "Ezeiruaku",
      "number": 90,
      "positions": ["defensive_end"],
      "team_id": 17,
      "attributes": {
        "overall": 74,
        "speed": 82,
        "strength": 78,
        "agility": 80,
        "awareness": 70,
        "discipline": 72,
        "composure": 70,
        "experience": 62,
        "penalty_technique": 72,
        "pass_rush": 78,
        "run_defense": 72,
        "power_moves": 75,
        "athleticism": 82,
        "potential": 80
      }
    },
    "1733": {
      "player_id": 1733,
      "first_name": "James",
      "last_name": "Houston",
      "number": 96,
      "positions": ["defensive_end"],
      "team_id": 17,
      "attributes": {
        "overall": 73,
        "speed": 82,
        "strength": 75,
        "agility": 80,
        "awareness": 72,
        "discipline": 75,
        "composure": 72,
        "experience": 70,
        "penalty_technique": 75,
        "pass_rush": 80,
        "run_defense": 68,
        "power_moves": 72,
        "quickness": 85,
        "motor": 80
      }
    },
    "1734": {
      "player_id": 1734,
      "first_name": "Sam",
      "last_name": "Williams",
      "number": 54,
      "positions": ["defensive_end"],
      "team_id": 17,
      "attributes": {
        "overall": 75,
        "speed": 80,
        "strength": 78,
        "agility": 78,
        "awareness": 75,
        "discipline": 78,
        "composure": 75,
        "experience": 75,
        "penalty_technique": 78,
        "pass_rush": 78,
        "run_defense": 72,
        "power_moves": 75,
        "consistency": 75,
        "depth_value": 78
      }
    },
    "1735": {
      "player_id": 1735,
      "first_name": "Osa",
      "last_name": "Odighizuwa",
      "number": 97,
      "positions": ["defensive_tackle"],
      "team_id": 17,
      "attributes": {
        "overall": 80,
        "speed": 75,
        "strength": 85,
        "agility": 75,
        "awareness": 82,
        "discipline": 82,
        "composure": 80,
        "experience": 75,
        "penalty_technique": 82,
        "pass_rush": 82,
        "run_defense": 80,
        "power_moves": 82,
        "technique": 82,
        "motor": 85
      }
    },
    "1736": {
      "player_id": 1736,
      "first_name": "Solomon",
      "last_name": "Thomas",
      "number": 93,
      "positions": ["defensive_tackle"],
      "team_id": 17,
      "attributes": {
        "overall": 78,
        "speed": 72,
        "strength": 85,
        "agility": 72,
        "awareness": 82,
        "discipline": 85,
        "composure": 82,
        "experience": 88,
        "penalty_technique": 85,
        "pass_rush": 75,
        "run_defense": 82,
        "power_moves": 80,
        "veteran_presence": 88,
        "consistency": 82
      }
    },
    "1737": {
      "player_id": 1737,
      "first_name": "Mazi",
      "last_name": "Smith",
      "number": 58,
      "positions": ["defensive_tackle"],
      "team_id": 17,
      "attributes": {
        "overall": 75,
        "speed": 70,
        "strength": 88,
        "agility": 68,
        "awareness": 72,
        "discipline": 75,
        "composure": 72,
        "experience": 68,
        "penalty_technique": 75,
        "pass_rush": 70,
        "run_defense": 82,
        "power_moves": 85,
        "size": 92,
        "potential": 82
      }
    },
    "1738": {
      "player_id": 1738,
      "first_name": "Jay",
      "last_name": "Toia",
      "number": 95,
      "positions": ["defensive_tackle"],
      "team_id": 17,
      "attributes": {
        "overall": 71,
        "speed": 68,
        "strength": 82,
        "agility": 68,
        "awareness": 68,
        "discipline": 72,
        "composure": 68,
        "experience": 65,
        "penalty_technique": 72,
        "pass_rush": 68,
        "run_defense": 75,
        "power_moves": 78,
        "development": 72,
        "depth": 72
      }
    },
    "1739": {
      "player_id": 1739,
      "first_name": "Perrion",
      "last_name": "Winfrey",
      "number": 91,
      "positions": ["defensive_tackle"],
      "team_id": 17,
      "attributes": {
        "overall": 72,
        "speed": 72,
        "strength": 82,
        "agility": 70,
        "awareness": 68,
        "discipline": 70,
        "composure": 68,
        "experience": 70,
        "penalty_technique": 70,
        "pass_rush": 75,
        "run_defense": 70,
        "power_moves": 78,
        "athleticism": 75,
        "motor": 78
      }
    },
    "1740": {
      "player_id": 1740,
      "first_name": "Marist",
      "last_name": "Liufau",
      "number": 48,
      "positions": ["linebacker"],
      "team_id": 17,
      "attributes": {
        "overall": 76,
        "speed": 82,
        "strength": 78,
        "agility": 82,
        "awareness": 78,
        "discipline": 80,
        "composure": 78,
        "experience": 70,
        "penalty_technique": 80,
        "pass_rush": 70,
        "run_defense": 80,
        "coverage": 78,
        "tackling": 82,
        "athleticism": 82
      }
    },
    "1741": {
      "player_id": 1741,
      "first_name": "Jack",
      "last_name": "Sanborn",
      "number": 57,
      "positions": ["linebacker"],
      "team_id": 17,
      "attributes": {
        "overall": 75,
        "speed": 78,
        "strength": 75,
        "agility": 80,
        "awareness": 80,
        "discipline": 82,
        "composure": 80,
        "experience": 75,
        "penalty_technique": 82,
        "pass_rush": 65,
        "run_defense": 78,
        "coverage": 80,
        "tackling": 82,
        "instincts": 82
      }
    },
    "1742": {
      "player_id": 1742,
      "first_name": "Kenneth",
      "last_name": "Murray",
      "number": 56,
      "positions": ["linebacker"],
      "team_id": 17,
      "attributes": {
        "overall": 77,
        "speed": 80,
        "strength": 80,
        "agility": 78,
        "awareness": 78,
        "discipline": 78,
        "composure": 78,
        "experience": 78,
        "penalty_technique": 78,
        "pass_rush": 68,
        "run_defense": 82,
        "coverage": 75,
        "tackling": 82,
        "athleticism": 82
      }
    },
    "1743": {
      "player_id": 1743,
      "first_name": "Damone",
      "last_name": "Clark",
      "number": 50,
      "positions": ["linebacker"],
      "team_id": 17,
      "attributes": {
        "overall": 78,
        "speed": 78,
        "strength": 80,
        "agility": 78,
        "awareness": 82,
        "discipline": 82,
        "composure": 80,
        "experience": 75,
        "penalty_technique": 82,
        "pass_rush": 65,
        "run_defense": 82,
        "coverage": 78,
        "tackling": 85,
        "leadership": 80
      }
    },
    "1744": {
      "player_id": 1744,
      "first_name": "Shemar",
      "last_name": "James",
      "number": 51,
      "positions": ["linebacker"],
      "team_id": 17,
      "attributes": {
        "overall": 70,
        "speed": 80,
        "strength": 72,
        "agility": 78,
        "awareness": 65,
        "discipline": 70,
        "composure": 65,
        "experience": 62,
        "penalty_technique": 70,
        "pass_rush": 68,
        "run_defense": 72,
        "coverage": 68,
        "tackling": 75,
        "potential": 78,
        "development": 75
      }
    },
    "1745": {
      "player_id": 1745,
      "first_name": "DaRon",
      "last_name": "Bland",
      "number": 26,
      "positions": ["cornerback"],
      "team_id": 17,
      "attributes": {
        "overall": 84,
        "speed": 85,
        "strength": 75,
        "agility": 85,
        "awareness": 85,
        "discipline": 85,
        "composure": 82,
        "experience": 70,
        "penalty_technique": 85,
        "man_coverage": 85,
        "zone_coverage": 88,
        "ball_skills": 90,
        "tackling": 80,
        "interceptions": 95
      }
    },
    "1746": {
      "player_id": 1746,
      "first_name": "Kaiir",
      "last_name": "Elam",
      "number": 27,
      "positions": ["cornerback"],
      "team_id": 17,
      "attributes": {
        "overall": 76,
        "speed": 85,
        "strength": 78,
        "agility": 82,
        "awareness": 72,
        "discipline": 75,
        "composure": 72,
        "experience": 70,
        "penalty_technique": 75,
        "man_coverage": 78,
        "zone_coverage": 75,
        "ball_skills": 80,
        "tackling": 75,
        "size": 85
      }
    },
    "1747": {
      "player_id": 1747,
      "first_name": "Trikweze",
      "last_name": "Bridges",
      "number": 29,
      "positions": ["cornerback"],
      "team_id": 17,
      "attributes": {
        "overall": 72,
        "speed": 82,
        "strength": 70,
        "agility": 82,
        "awareness": 68,
        "discipline": 72,
        "composure": 68,
        "experience": 68,
        "penalty_technique": 72,
        "man_coverage": 75,
        "zone_coverage": 72,
        "ball_skills": 75,
        "tackling": 68,
        "development": 75
      }
    },
    "1748": {
      "player_id": 1748,
      "first_name": "Reddy",
      "last_name": "Steward",
      "number": 25,
      "positions": ["cornerback"],
      "team_id": 17,
      "attributes": {
        "overall": 71,
        "speed": 80,
        "strength": 72,
        "agility": 80,
        "awareness": 68,
        "discipline": 72,
        "composure": 68,
        "experience": 68,
        "penalty_technique": 72,
        "man_coverage": 72,
        "zone_coverage": 75,
        "ball_skills": 72,
        "tackling": 70,
        "depth_value": 72
      }
    },
    "1749": {
      "player_id": 1749,
      "first_name": "C.J.",
      "last_name": "Goodwin",
      "number": 22,
      "positions": ["cornerback"],
      "team_id": 17,
      "attributes": {
        "overall": 73,
        "speed": 82,
        "strength": 68,
        "agility": 82,
        "awareness": 82,
        "discipline": 85,
        "composure": 82,
        "experience": 88,
        "penalty_technique": 85,
        "man_coverage": 70,
        "zone_coverage": 75,
        "ball_skills": 72,
        "tackling": 75,
        "special_teams": 90,
        "veteran_presence": 88
      }
    },
    "1750": {
      "player_id": 1750,
      "first_name": "Malik",
      "last_name": "Hooker",
      "number": 28,
      "positions": ["safety"],
      "team_id": 17,
      "attributes": {
        "overall": 81,
        "speed": 88,
        "strength": 75,
        "agility": 85,
        "awareness": 88,
        "discipline": 85,
        "composure": 85,
        "experience": 85,
        "penalty_technique": 85,
        "man_coverage": 78,
        "zone_coverage": 88,
        "ball_skills": 88,
        "tackling": 78,
        "range": 90,
        "instincts": 88
      }
    },
    "1751": {
      "player_id": 1751,
      "first_name": "Juanyeh",
      "last_name": "Thomas",
      "number": 20,
      "positions": ["safety"],
      "team_id": 17,
      "attributes": {
        "overall": 75,
        "speed": 82,
        "strength": 78,
        "agility": 78,
        "awareness": 75,
        "discipline": 78,
        "composure": 75,
        "experience": 75,
        "penalty_technique": 78,
        "man_coverage": 72,
        "zone_coverage": 78,
        "ball_skills": 78,
        "tackling": 80,
        "versatility": 80
      }
    },
    "1752": {
      "player_id": 1752,
      "first_name": "Markquese",
      "last_name": "Bell",
      "number": 21,
      "positions": ["safety"],
      "team_id": 17,
      "attributes": {
        "overall": 73,
        "speed": 80,
        "strength": 78,
        "agility": 78,
        "awareness": 72,
        "discipline": 75,
        "composure": 72,
        "experience": 68,
        "penalty_technique": 75,
        "man_coverage": 68,
        "zone_coverage": 75,
        "ball_skills": 75,
        "tackling": 78,
        "run_support": 80,
        "development": 75
      }
    },
    "1753": {
      "player_id": 1753,
      "first_name": "Bryan",
      "last_name": "Anger",
      "number": 5,
      "positions": ["punter"],
      "team_id": 17,
      "attributes": {
        "overall": 82,
        "speed": 65,
        "strength": 72,
        "agility": 68,
        "awareness": 85,
        "discipline": 88,
        "composure": 85,
        "experience": 92,
        "penalty_technique": 88,
        "punt_power": 88,
        "punt_accuracy": 85,
        "hang_time": 85,
        "directional_punting": 88,
        "consistency": 88
      }
    },
    "1754": {
      "player_id": 1754,
      "first_name": "Trent",
      "last_name": "Sieg",
      "number": 45,
      "positions": ["long_snapper"],
      "team_id": 17,
      "attributes": {
        "overall": 77,
        "speed": 65,
        "strength": 78,
        "agility": 68,
        "awareness": 82,
        "discipline": 88,
        "composure": 82,
        "experience": 75,
        "penalty_technique": 88,
        "snap_accuracy": 90,
        "consistency": 88,
        "leadership": 78,
        "reliability": 90
      }
    }
  }
}